assets/postgres-pro.png
examples/movie-app.md
src/postgres_mcp/__init__.py
src/postgres_mcp/artifacts.py
src/postgres_mcp/server.py
src/postgres_mcp/database_health/__init__.py
src/postgres_mcp/database_health/buffer_health_calc.py
src/postgres_mcp/database_health/connection_health_calc.py
src/postgres_mcp/database_health/constraint_health_calc.py
src/postgres_mcp/database_health/database_health.py
src/postgres_mcp/database_health/index_health_calc.py
src/postgres_mcp/database_health/replication_calc.py
src/postgres_mcp/database_health/sequence_health_calc.py
src/postgres_mcp/database_health/vacuum_health_calc.py
src/postgres_mcp/dta/__init__.py
src/postgres_mcp/dta/dta_calc.py
src/postgres_mcp/dta/dta_tools.py
src/postgres_mcp/explain/README.md
src/postgres_mcp/explain/__init__.py
src/postgres_mcp/explain/explain_plan.py
src/postgres_mcp/sql/__init__.py
src/postgres_mcp/sql/bind_params.py
src/postgres_mcp/sql/extension_utils.py
src/postgres_mcp/sql/index.py
src/postgres_mcp/sql/safe_sql.py
src/postgres_mcp/sql/sql_driver.py
src/postgres_mcp/top_queries/__init__.py
src/postgres_mcp/top_queries/top_queries_calc.py
tests/Dockerfile.postgres-hypopg
tests/README.md
tests/conftest.py
tests/utils.py
tests/integration/test_top_queries_integration.py
tests/integration/dta/test_dta_calc_integration.py
tests/unit/test_access_mode.py
tests/unit/database_health/test_database_health_tool.py
tests/unit/dta/test_dta_calc.py
tests/unit/explain/test_explain_plan.py
tests/unit/explain/test_explain_plan_real_db.py
tests/unit/explain/test_server.py
tests/unit/explain/test_server_integration.py
tests/unit/sql/test_db_conn_pool.py
tests/unit/sql/test_obfuscate_password.py
tests/unit/sql/test_readonly_enforcement.py
tests/unit/sql/test_safe_sql.py
tests/unit/sql/test_sql_driver.py
tests/unit/top_queries/test_top_queries_calc.py
orange_postgres_mcp-0.1.1.dist-info/METADATA
orange_postgres_mcp-0.1.1.dist-info/WHEEL
orange_postgres_mcp-0.1.1.dist-info/entry_points.txt
orange_postgres_mcp-0.1.1.dist-info/licenses/LICENSE
orange_postgres_mcp-0.1.1.dist-info/RECORD
